cloudmesh_storage-4.0.14-py3.8-nspkg.pth
cloudmesh/storage/Provider.py
cloudmesh/storage/__init__.py
cloudmesh/storage/__version__.py
cloudmesh/storage/command/__init__.py
cloudmesh/storage/command/storage.py
cloudmesh/storage/provider/__init__.py
cloudmesh/storage/provider/storage.py
cloudmesh/storage/provider/awss3/Provider.py
cloudmesh/storage/provider/awss3/__init__.py
cloudmesh/storage/provider/azureblob/Provider.py
cloudmesh/storage/provider/azureblob/__init__.py
cloudmesh/storage/provider/box/Provider.py
cloudmesh/storage/provider/box/__init__.py
cloudmesh/storage/provider/gdrive/Provider.py
cloudmesh/storage/provider/gdrive/__init__.py
cloudmesh/storage/provider/local/Provider.py
cloudmesh/storage/provider/local/__init__.py
cloudmesh/storage/provider/parallelawss3/Provider.py
cloudmesh/storage/provider/parallelawss3/__init__.py
cloudmesh/storage/queue/StorageQueue.py
cloudmesh/storage/queue/__init__.py
cloudmesh/storage/queue/test.py
cloudmesh/vdir/__init__.py
cloudmesh/vdir/api/__init__.py
cloudmesh/vdir/api/manager.py
cloudmesh/vdir/command/__init__.py
cloudmesh/vdir/command/vdir.py
cloudmesh_storage-4.0.14.dist-info/LICENSE
cloudmesh_storage-4.0.14.dist-info/METADATA
cloudmesh_storage-4.0.14.dist-info/WHEEL
cloudmesh_storage-4.0.14.dist-info/namespace_packages.txt
cloudmesh_storage-4.0.14.dist-info/top_level.txt
cloudmesh_storage-4.0.14.dist-info/RECORD
