Metadata-Version: 2.1
Name: cloudmesh-storage
Version: 4.0.14
Summary: A command called storage and foo for the cloudmesh shell
Home-page: https://github.com/cloudmesh/cloudmesh-storage
Author: Gregor von Laszewski
Author-email: laszewski@gmail.com
License: Apache 2.0
Platform: UNKNOWN
Classifier: Development Status :: 5 - Production/Stable
Classifier: Environment :: Web Environment
Classifier: Intended Audience :: Developers
Classifier: License :: OSI Approved :: BSD License
Classifier: Operating System :: OS Independent
Classifier: Programming Language :: Python
Classifier: Programming Language :: Python :: 2
Classifier: Programming Language :: Python :: 3
Requires-Dist: apiclient
Requires-Dist: boxsdk
Requires-Dist: boto3
Requires-Dist: botocore
Requires-Dist: httplib2
Requires-Dist: google-api-python-client
Requires-Dist: google-auth
Requires-Dist: google-auth-httplib2
Requires-Dist: python-magic
Requires-Dist: oauth2client
Requires-Dist: azure
Requires-Dist: azure-storage-common
Requires-Dist: azure-storage-nspkg
Requires-Dist: azure-storage-blob
Requires-Dist: cloudmesh-common
Requires-Dist: cloudmesh-cmd5
Requires-Dist: cloudmesh-abstract
Requires-Dist: cloudmesh-configuration
